{
  "instituicao_id": "pmesp",
  "instituicao_nome": "Polícia Militar do Estado de São Paulo",
  "sigla": "PMESP",
  "uf": "SP",
  "tema": "concursos",
  "status": "rascunho",
  "titulo": "PMESP: concursos, páginas oficiais",
  "resumo": "Não encontrado em fonte oficial (para atualização do resumo específico de concursos).",
  "edital": "não encontrado em fonte oficial",
  "salario": "não encontrado em fonte oficial",
  "vagas": "não encontrado em fonte oficial",
  "cotas": "não encontrado em fonte oficial",
  "idade": "não encontrado em fonte oficial",
  "escolaridade": "não encontrado em fonte oficial",
  "materias": "não encontrado em fonte oficial",
  "banca": "não encontrado em fonte oficial",
  "inscritos": "não encontrado em fonte oficial",
  "etapas": "não encontrado em fonte oficial",
  "cfsd": "não encontrado em fonte oficial",
  "estagio": "não encontrado em fonte oficial",
  "validade": "não encontrado em fonte oficial",
  "previsao": "não encontrado em fonte oficial",
  "site": "https://www.policiamilitar.sp.gov.br/",
  "fontes": [
    {
      "titulo": "Página institucional da Polícia Militar do Estado de São Paulo (acesso ao menu “Concursos”)",
      "url": "https://www.policiamilitar.sp.gov.br/",
      "tipo": "fonte oficial",
      "data_consulta": "2026-05-17"
    }
  ],
  "ultima_pesquisa": "2026-05-17",
  "nivel_confianca": "baixo",
  "precisa_revisao_humana": true,
  "alertas": [
    "Fontes oficiais fornecidas no prompt não trazem texto/links de editais e informações de concursos; apenas conteúdo institucional e indicação de menu “Concursos”."
  ]
}
